{
    "/assets/js/app.js": "/assets/js/app.js?id=7c8a672819cfec4e13c8",
    "/assets/css/app.css": "/assets/css/app.css?id=d598ddf87765be56b5d0",
    "/assets/js/dashboard/app.js": "/assets/js/dashboard/app.js?id=3a3f96190e34e94b8ad6",
    "/assets/js/expert/app.js": "/assets/js/expert/app.js?id=264947c047f1cb1e4e08",
    "/assets/js/global/app.js": "/assets/js/global/app.js?id=e1ba9f854dab69898c6a",
    "/assets/js/global/newsletter.js": "/assets/js/global/newsletter.js?id=da51bd4c096e8e4848ea",
    "/assets/js/global/register.js": "/assets/js/global/register.js?id=b6bddd50bec663fd9538",
    "/assets/js/student/app.js": "/assets/js/student/app.js?id=f6db20d9bd583253d55b"
}
