{
    "/assets/js/app.js": "/assets/js/app.js?id=7c8a672819cfec4e13c8",
    "/assets/css/app.css": "/assets/css/app.css?id=eb5bad1783b9f1b9727c",
    "/assets/js/dashboard/app.js": "/assets/js/dashboard/app.js?id=29bf6678c58930a2ae62",
    "/assets/js/expert/app.js": "/assets/js/expert/app.js?id=52cc1ddfcc64625add92",
    "/assets/js/global/app.js": "/assets/js/global/app.js?id=0b40e193eb56f5c59add",
    "/assets/js/global/register.js": "/assets/js/global/register.js?id=fc17bfbcefed634fccfd",
    "/assets/js/student/app.js": "/assets/js/student/app.js?id=827e8ca2dc71badca393"
}
